[
  {
    "org": "bostonglobe",
    "name": "snap-map",
    "full_name": "BostonGlobe/snap-map",
    "created_at": "2011-06-28 02:01:01",
    "fork": false,
    "stargazers_count": 5,
    "forks_count": 2,
    "language": "JavaScript"
  },
  {
    "org": "bostonglobe",
    "name": "tweet-map",
    "full_name": "BostonGlobe/tweet-map",
    "created_at": "2011-09-30 18:49:19",
    "fork": false,
    "stargazers_count": 1,
    "forks_count": 0,
    "language": null
  },
  {
    "org": "bostonglobe",
    "name": "snip",
    "full_name": "BostonGlobe/snip",
    "created_at": "2012-01-05 19:09:04",
    "fork": false,
    "stargazers_count": 1,
    "forks_count": 0,
    "language": null
  },
  {
    "org": "bostonglobe",
    "name": "where-at",
    "full_name": "BostonGlobe/where-at",
    "created_at": "2012-02-16 19:35:00",
    "fork": false,
    "stargazers_count": 0,
    "forks_count": 0,
    "language": "JavaScript"
  },
  {
    "org": "bostonglobe",
    "name": "artmap",
    "full_name": "BostonGlobe/artmap",
    "created_at": "2012-05-18 07:18:07",
    "fork": false,
    "stargazers_count": 1,
    "forks_count": 0,
    "language": "JavaScript"
  },
  {
    "org": "bostonglobe",
    "name": "swatch-libraries",
    "full_name": "BostonGlobe/swatch-libraries",
    "created_at": "2013-05-02 14:04:39",
    "fork": false,
    "stargazers_count": 2,
    "forks_count": 0,
    "language": null
  },
  {
    "org": "bostonglobe",
    "name": "logos",
    "full_name": "BostonGlobe/logos",
    "created_at": "2013-05-07 17:16:56",
    "fork": false,
    "stargazers_count": 2,
    "forks_count": 1,
    "language": null
  },
  {
    "org": "bostonglobe",
    "name": "shapefiles",
    "full_name": "BostonGlobe/shapefiles",
    "created_at": "2013-08-26 20:43:35",
    "fork": false,
    "stargazers_count": 0,
    "forks_count": 0,
    "language": null
  },
  {
    "org": "bostonglobe",
    "name": "generator-globeproject",
    "full_name": "BostonGlobe/generator-globeproject",
    "created_at": "2014-03-19 23:06:45",
    "fork": false,
    "stargazers_count": 7,
    "forks_count": 1,
    "language": "HTML"
  },
  {
    "org": "bostonglobe",
    "name": "04-01-2014_whyIRun",
    "full_name": "BostonGlobe/04-01-2014_whyIRun",
    "created_at": "2014-03-21 22:45:30",
    "fork": false,
    "stargazers_count": 0,
    "forks_count": 0,
    "language": "JavaScript"
  },
  {
    "org": "bostonglobe",
    "name": "04-15-2014-panorama",
    "full_name": "BostonGlobe/04-15-2014-panorama",
    "created_at": "2014-04-16 21:31:41",
    "fork": false,
    "stargazers_count": 4,
    "forks_count": 0,
    "language": "JavaScript"
  },
  {
    "org": "bostonglobe",
    "name": "04-21-2014-marathonwinners",
    "full_name": "BostonGlobe/04-21-2014-marathonwinners",
    "created_at": "2014-04-18 18:46:36",
    "fork": false,
    "stargazers_count": 0,
    "forks_count": 0,
    "language": "JavaScript"
  },
  {
    "org": "bostonglobe",
    "name": "interactive-modules",
    "full_name": "BostonGlobe/interactive-modules",
    "created_at": "2014-05-14 21:25:04",
    "fork": false,
    "stargazers_count": 2,
    "forks_count": 0,
    "language": "JavaScript"
  },
  {
    "org": "bostonglobe",
    "name": "data_utilities",
    "full_name": "BostonGlobe/data_utilities",
    "created_at": "2014-05-15 23:12:51",
    "fork": false,
    "stargazers_count": 1,
    "forks_count": 0,
    "language": "Python"
  },
  {
    "org": "bostonglobe",
    "name": "brief",
    "full_name": "BostonGlobe/brief",
    "created_at": "2014-06-21 03:32:57",
    "fork": false,
    "stargazers_count": 0,
    "forks_count": 0,
    "language": "HTML"
  },
  {
    "org": "bostonglobe",
    "name": "ap-election-loader",
    "full_name": "BostonGlobe/ap-election-loader",
    "created_at": "2014-06-24 22:20:07",
    "fork": true,
    "stargazers_count": 0,
    "forks_count": 0,
    "language": "Ruby"
  },
  {
    "org": "bostonglobe",
    "name": "07-30-2014-pedestrians",
    "full_name": "BostonGlobe/07-30-2014-pedestrians",
    "created_at": "2014-07-25 20:57:15",
    "fork": false,
    "stargazers_count": 0,
    "forks_count": 0,
    "language": "CSS"
  },
  {
    "org": "bostonglobe",
    "name": "scraper_skeleton",
    "full_name": "BostonGlobe/scraper_skeleton",
    "created_at": "2014-08-22 22:59:11",
    "fork": false,
    "stargazers_count": 1,
    "forks_count": 0,
    "language": "JavaScript"
  },
  {
    "org": "bostonglobe",
    "name": "11-04-2014-elections",
    "full_name": "BostonGlobe/11-04-2014-elections",
    "created_at": "2014-09-24 19:33:22",
    "fork": false,
    "stargazers_count": 3,
    "forks_count": 0,
    "language": "JavaScript"
  },
  {
    "org": "bostonglobe",
    "name": "61fresh",
    "full_name": "BostonGlobe/61fresh",
    "created_at": "2014-11-11 00:22:42",
    "fork": false,
    "stargazers_count": 0,
    "forks_count": 1,
    "language": "Python"
  },
  {
    "org": "bostonglobe",
    "name": "snowfall-totals",
    "full_name": "BostonGlobe/snowfall-totals",
    "created_at": "2014-11-26 16:31:58",
    "fork": false,
    "stargazers_count": 0,
    "forks_count": 0,
    "language": "HTML"
  },
  {
    "org": "bostonglobe",
    "name": "poweroutages",
    "full_name": "BostonGlobe/poweroutages",
    "created_at": "2014-12-01 21:44:14",
    "fork": false,
    "stargazers_count": 1,
    "forks_count": 0,
    "language": "JavaScript"
  },
  {
    "org": "bostonglobe",
    "name": "tsarnaev-cards",
    "full_name": "BostonGlobe/tsarnaev-cards",
    "created_at": "2015-01-05 20:02:13",
    "fork": false,
    "stargazers_count": 1,
    "forks_count": 0,
    "language": "HTML"
  },
  {
    "org": "bostonglobe",
    "name": "snowfall_scraper",
    "full_name": "BostonGlobe/snowfall_scraper",
    "created_at": "2015-01-27 20:40:50",
    "fork": false,
    "stargazers_count": 0,
    "forks_count": 0,
    "language": "Shell"
  },
  {
    "org": "bostonglobe",
    "name": "america_ocean",
    "full_name": "BostonGlobe/america_ocean",
    "created_at": "2015-02-03 20:01:16",
    "fork": false,
    "stargazers_count": 0,
    "forks_count": 0,
    "language": "CartoCSS"
  },
  {
    "org": "bostonglobe",
    "name": "02-23-2015_bondbill",
    "full_name": "BostonGlobe/02-23-2015_bondbill",
    "created_at": "2015-02-24 04:59:07",
    "fork": false,
    "stargazers_count": 0,
    "forks_count": 0,
    "language": "HTML"
  },
  {
    "org": "bostonglobe",
    "name": "03-01-2015-boom",
    "full_name": "BostonGlobe/03-01-2015-boom",
    "created_at": "2015-03-01 03:55:07",
    "fork": false,
    "stargazers_count": 0,
    "forks_count": 0,
    "language": "HTML"
  },
  {
    "org": "bostonglobe",
    "name": "icerinks",
    "full_name": "BostonGlobe/icerinks",
    "created_at": "2015-03-03 21:32:00",
    "fork": false,
    "stargazers_count": 0,
    "forks_count": 0,
    "language": "HTML"
  },
  {
    "org": "bostonglobe",
    "name": "potholes",
    "full_name": "BostonGlobe/potholes",
    "created_at": "2015-03-03 23:54:24",
    "fork": false,
    "stargazers_count": 0,
    "forks_count": 0,
    "language": "HTML"
  },
  {
    "org": "bostonglobe",
    "name": "chinatown",
    "full_name": "BostonGlobe/chinatown",
    "created_at": "2015-03-24 20:01:57",
    "fork": false,
    "stargazers_count": 0,
    "forks_count": 0,
    "language": "HTML"
  },
  {
    "org": "bostonglobe",
    "name": "schoolbuses",
    "full_name": "BostonGlobe/schoolbuses",
    "created_at": "2015-04-03 16:37:31",
    "fork": false,
    "stargazers_count": 0,
    "forks_count": 0,
    "language": "HTML"
  },
  {
    "org": "bostonglobe",
    "name": "stateparks",
    "full_name": "BostonGlobe/stateparks",
    "created_at": "2015-04-28 18:11:01",
    "fork": false,
    "stargazers_count": 0,
    "forks_count": 0,
    "language": "HTML"
  },
  {
    "org": "bostonglobe",
    "name": "news-apps-docs",
    "full_name": "BostonGlobe/news-apps-docs",
    "created_at": "2015-05-11 11:13:24",
    "fork": false,
    "stargazers_count": 2,
    "forks_count": 1,
    "language": "JavaScript"
  },
  {
    "org": "bostonglobe",
    "name": "map-recipes",
    "full_name": "BostonGlobe/map-recipes",
    "created_at": "2015-05-16 18:53:41",
    "fork": false,
    "stargazers_count": 10,
    "forks_count": 1,
    "language": "Makefile"
  },
  {
    "org": "bostonglobe",
    "name": "06-03-2015-nba",
    "full_name": "BostonGlobe/06-03-2015-nba",
    "created_at": "2015-05-21 20:31:33",
    "fork": false,
    "stargazers_count": 0,
    "forks_count": 1,
    "language": null
  },
  {
    "org": "bostonglobe",
    "name": "social-image-maker",
    "full_name": "BostonGlobe/social-image-maker",
    "created_at": "2015-06-15 12:50:41",
    "fork": false,
    "stargazers_count": 7,
    "forks_count": 3,
    "language": "JavaScript"
  },
  {
    "org": "bostonglobe",
    "name": "news-apps-style-guide",
    "full_name": "BostonGlobe/news-apps-style-guide",
    "created_at": "2015-06-17 16:55:14",
    "fork": false,
    "stargazers_count": 1,
    "forks_count": 0,
    "language": null
  },
  {
    "org": "bostonglobe",
    "name": "slush-globegraphic",
    "full_name": "BostonGlobe/slush-globegraphic",
    "created_at": "2015-06-17 21:42:38",
    "fork": false,
    "stargazers_count": 0,
    "forks_count": 0,
    "language": "JavaScript"
  },
  {
    "org": "bostonglobe",
    "name": "pym-iframe-resizer",
    "full_name": "BostonGlobe/pym-iframe-resizer",
    "created_at": "2015-06-18 23:39:10",
    "fork": false,
    "stargazers_count": 1,
    "forks_count": 0,
    "language": "JavaScript"
  },
  {
    "org": "bostonglobe",
    "name": "2015-6-23_vaccines",
    "full_name": "BostonGlobe/2015-6-23_vaccines",
    "created_at": "2015-06-23 18:26:33",
    "fork": false,
    "stargazers_count": 0,
    "forks_count": 0,
    "language": "JavaScript"
  },
  {
    "org": "bostonglobe",
    "name": "slush-globeapp",
    "full_name": "BostonGlobe/slush-globeapp",
    "created_at": "2015-07-09 13:14:21",
    "fork": false,
    "stargazers_count": 5,
    "forks_count": 1,
    "language": "JavaScript"
  },
  {
    "org": "bostonglobe",
    "name": "globe-graphic-template",
    "full_name": "BostonGlobe/globe-graphic-template",
    "created_at": "2015-09-12 02:44:12",
    "fork": false,
    "stargazers_count": 5,
    "forks_count": 2,
    "language": "CSS"
  },
  {
    "org": "bostonglobe",
    "name": "slushgraphic-template",
    "full_name": "BostonGlobe/slushgraphic-template",
    "created_at": "2015-09-13 06:01:45",
    "fork": false,
    "stargazers_count": 0,
    "forks_count": 0,
    "language": "JavaScript"
  },
  {
    "org": "bostonglobe",
    "name": "2015-09-23_mcas-districts",
    "full_name": "BostonGlobe/2015-09-23_mcas-districts",
    "created_at": "2015-09-23 22:23:50",
    "fork": false,
    "stargazers_count": 0,
    "forks_count": 0,
    "language": "CSS"
  },
  {
    "org": "bostonglobe",
    "name": "globe-css-generator",
    "full_name": "BostonGlobe/globe-css-generator",
    "created_at": "2015-09-25 17:26:01",
    "fork": false,
    "stargazers_count": 0,
    "forks_count": 0,
    "language": "JavaScript"
  },
  {
    "org": "bostonglobe",
    "name": "2015-09-28_huts",
    "full_name": "BostonGlobe/2015-09-28_huts",
    "created_at": "2015-10-01 17:10:51",
    "fork": false,
    "stargazers_count": 0,
    "forks_count": 0,
    "language": "HTML"
  },
  {
    "org": "bostonglobe",
    "name": "2015-10-01_amp",
    "full_name": "BostonGlobe/2015-10-01_amp",
    "created_at": "2015-10-13 16:48:04",
    "fork": false,
    "stargazers_count": 0,
    "forks_count": 0,
    "language": "HTML"
  },
  {
    "org": "bostonglobe",
    "name": "2015-10-14_deer",
    "full_name": "BostonGlobe/2015-10-14_deer",
    "created_at": "2015-10-15 03:55:11",
    "fork": false,
    "stargazers_count": 0,
    "forks_count": 0,
    "language": "HTML"
  },
  {
    "org": "bostonglobe",
    "name": "waypoints",
    "full_name": "BostonGlobe/waypoints",
    "created_at": "2015-10-25 03:58:22",
    "fork": true,
    "stargazers_count": 0,
    "forks_count": 0,
    "language": "JavaScript"
  },
  {
    "org": "bostonglobe",
    "name": "income_inequality",
    "full_name": "BostonGlobe/income_inequality",
    "created_at": "2015-11-13 14:22:46",
    "fork": false,
    "stargazers_count": 0,
    "forks_count": 0,
    "language": "Makefile"
  },
  {
    "org": "bostonglobe",
    "name": "election-utils",
    "full_name": "BostonGlobe/election-utils",
    "created_at": "2016-01-07 19:25:31",
    "fork": false,
    "stargazers_count": 4,
    "forks_count": 0,
    "language": "JavaScript"
  },
  {
    "org": "bostonglobe",
    "name": "pym.js",
    "full_name": "BostonGlobe/pym.js",
    "created_at": "2016-01-08 15:15:09",
    "fork": true,
    "stargazers_count": 0,
    "forks_count": 0,
    "language": "JavaScript"
  },
  {
    "org": "bostonglobe",
    "name": "2016_primaries_smt",
    "full_name": "BostonGlobe/2016_primaries_smt",
    "created_at": "2016-01-14 19:47:10",
    "fork": false,
    "stargazers_count": 1,
    "forks_count": 0,
    "language": "JavaScript"
  },
  {
    "org": "bostonglobe",
    "name": "scribblelive_widget",
    "full_name": "BostonGlobe/scribblelive_widget",
    "created_at": "2016-01-19 13:55:38",
    "fork": false,
    "stargazers_count": 0,
    "forks_count": 0,
    "language": "HTML"
  },
  {
    "org": "bostonglobe",
    "name": "2016_primaries--landing",
    "full_name": "BostonGlobe/2016_primaries--landing",
    "created_at": "2016-01-26 21:16:38",
    "fork": false,
    "stargazers_count": 0,
    "forks_count": 0,
    "language": "JavaScript"
  },
  {
    "org": "bostonglobe",
    "name": "2016-01-27_keolis-delays",
    "full_name": "BostonGlobe/2016-01-27_keolis-delays",
    "created_at": "2016-01-28 13:29:43",
    "fork": false,
    "stargazers_count": 0,
    "forks_count": 0,
    "language": "Jupyter Notebook"
  },
  {
    "org": "bostonglobe",
    "name": "2016-02-08_snowfall_map",
    "full_name": "BostonGlobe/2016-02-08_snowfall_map",
    "created_at": "2016-02-08 21:39:00",
    "fork": false,
    "stargazers_count": 0,
    "forks_count": 0,
    "language": "HTML"
  },
  {
    "org": "bostonglobe",
    "name": "super_tuesday_summary",
    "full_name": "BostonGlobe/super_tuesday_summary",
    "created_at": "2016-02-22 23:24:36",
    "fork": false,
    "stargazers_count": 0,
    "forks_count": 0,
    "language": "JavaScript"
  },
  {
    "org": "bostonglobe",
    "name": "2016_delegate_tracker",
    "full_name": "BostonGlobe/2016_delegate_tracker",
    "created_at": "2016-02-24 17:16:29",
    "fork": false,
    "stargazers_count": 0,
    "forks_count": 0,
    "language": "HTML"
  },
  {
    "org": "bostonglobe",
    "name": "2016_primaries_map",
    "full_name": "BostonGlobe/2016_primaries_map",
    "created_at": "2016-02-28 02:31:57",
    "fork": false,
    "stargazers_count": 0,
    "forks_count": 0,
    "language": "JavaScript"
  },
  {
    "org": "bostonglobe",
    "name": "sports-charts",
    "full_name": "BostonGlobe/sports-charts",
    "created_at": "2016-03-09 13:23:07",
    "fork": false,
    "stargazers_count": 0,
    "forks_count": 2,
    "language": "JavaScript"
  },
  {
    "org": "bostonglobe",
    "name": "charts",
    "full_name": "BostonGlobe/charts",
    "created_at": "2016-03-17 16:23:21",
    "fork": false,
    "stargazers_count": 0,
    "forks_count": 0,
    "language": "JavaScript"
  },
  {
    "org": "bostonglobe",
    "name": "nba-shot-zones",
    "full_name": "BostonGlobe/nba-shot-zones",
    "created_at": "2016-03-17 18:22:26",
    "fork": false,
    "stargazers_count": 1,
    "forks_count": 0,
    "language": "JavaScript"
  },
  {
    "org": "bostonglobe",
    "name": "pym-test",
    "full_name": "BostonGlobe/pym-test",
    "created_at": "2016-05-19 12:33:46",
    "fork": false,
    "stargazers_count": 0,
    "forks_count": 0,
    "language": "JavaScript"
  },
  {
    "org": "bostonglobe",
    "name": "trump-transcripts",
    "full_name": "BostonGlobe/trump-transcripts",
    "created_at": "2016-05-24 16:22:27",
    "fork": false,
    "stargazers_count": 0,
    "forks_count": 0,
    "language": "HTML"
  },
  {
    "org": "bostonglobe",
    "name": "housing-stock",
    "full_name": "BostonGlobe/housing-stock",
    "created_at": "2016-07-07 18:48:44",
    "fork": false,
    "stargazers_count": 0,
    "forks_count": 0,
    "language": "HTML"
  },
  {
    "org": "bostonglobe",
    "name": "weather-distributions",
    "full_name": "BostonGlobe/weather-distributions",
    "created_at": "2016-07-26 22:11:42",
    "fork": false,
    "stargazers_count": 0,
    "forks_count": 0,
    "language": "HTML"
  },
  {
    "org": "bostonglobe",
    "name": "death",
    "full_name": "BostonGlobe/death",
    "created_at": "2016-11-17 21:01:11",
    "fork": false,
    "stargazers_count": 0,
    "forks_count": 0,
    "language": "HTML"
  },
  {
    "org": "bostonglobe",
    "name": "snow",
    "full_name": "BostonGlobe/snow",
    "created_at": "2016-11-18 22:52:35",
    "fork": false,
    "stargazers_count": 0,
    "forks_count": 1,
    "language": "JavaScript"
  },
  {
    "org": "bostonglobe",
    "name": "gpreview",
    "full_name": "BostonGlobe/gpreview",
    "created_at": "2016-12-01 23:45:22",
    "fork": false,
    "stargazers_count": 0,
    "forks_count": 0,
    "language": "HTML"
  },
  {
    "org": "bostonglobe",
    "name": "ai2html",
    "full_name": "BostonGlobe/ai2html",
    "created_at": "2016-12-04 22:50:35",
    "fork": true,
    "stargazers_count": 0,
    "forks_count": 0,
    "language": "JavaScript"
  },
  {
    "org": "bostonglobe",
    "name": "my-shoes",
    "full_name": "BostonGlobe/my-shoes",
    "created_at": "2017-02-13 22:44:01",
    "fork": false,
    "stargazers_count": 1,
    "forks_count": 0,
    "language": "JavaScript"
  },
  {
    "org": "bostonglobe",
    "name": "spotlight-mental-health",
    "full_name": "BostonGlobe/spotlight-mental-health",
    "created_at": "2017-03-09 19:52:33",
    "fork": false,
    "stargazers_count": 0,
    "forks_count": 0,
    "language": "HTML"
  },
  {
    "org": "bostonglobe",
    "name": "tomcat-servedby-valve",
    "full_name": "BostonGlobe/tomcat-servedby-valve",
    "created_at": "2017-03-12 23:30:53",
    "fork": false,
    "stargazers_count": 0,
    "forks_count": 0,
    "language": "Java"
  },
  {
    "org": "bostonglobe",
    "name": "maintenance",
    "full_name": "BostonGlobe/maintenance",
    "created_at": "2017-03-23 19:31:44",
    "fork": false,
    "stargazers_count": 0,
    "forks_count": 1,
    "language": "HTML"
  },
  {
    "org": "bostonglobe",
    "name": "FYI",
    "full_name": "BostonGlobe/FYI",
    "created_at": "2017-03-30 17:46:36",
    "fork": false,
    "stargazers_count": 5,
    "forks_count": 0,
    "language": null
  },
  {
    "org": "bostonglobe",
    "name": "boston-revealed",
    "full_name": "BostonGlobe/boston-revealed",
    "created_at": "2017-04-12 20:48:15",
    "fork": false,
    "stargazers_count": 0,
    "forks_count": 0,
    "language": "HTML"
  },
  {
    "org": "bostonglobe",
    "name": "hack-days",
    "full_name": "BostonGlobe/hack-days",
    "created_at": "2017-04-21 18:01:24",
    "fork": false,
    "stargazers_count": 0,
    "forks_count": 0,
    "language": null
  },
  {
    "org": "bostonglobe",
    "name": "globe-trending",
    "full_name": "BostonGlobe/globe-trending",
    "created_at": "2017-05-03 13:55:40",
    "fork": false,
    "stargazers_count": 0,
    "forks_count": 0,
    "language": "CSS"
  },
  {
    "org": "bostonglobe",
    "name": "Primary-Vagrant",
    "full_name": "BostonGlobe/Primary-Vagrant",
    "created_at": "2017-05-04 11:41:13",
    "fork": true,
    "stargazers_count": 0,
    "forks_count": 0,
    "language": "PHP"
  },
  {
    "org": "bostonglobe",
    "name": "morrissey-stories",
    "full_name": "BostonGlobe/morrissey-stories",
    "created_at": "2017-05-26 17:51:37",
    "fork": false,
    "stargazers_count": 0,
    "forks_count": 0,
    "language": "JavaScript"
  },
  {
    "org": "bostonglobe",
    "name": "boston-rocks",
    "full_name": "BostonGlobe/boston-rocks",
    "created_at": "2017-06-05 16:22:20",
    "fork": false,
    "stargazers_count": 0,
    "forks_count": 0,
    "language": "HTML"
  },
  {
    "org": "bostonglobe",
    "name": "alcohol-graphic",
    "full_name": "BostonGlobe/alcohol-graphic",
    "created_at": "2017-07-03 19:41:52",
    "fork": false,
    "stargazers_count": 0,
    "forks_count": 0,
    "language": "HTML"
  },
  {
    "org": "bostonglobe",
    "name": "ShootingsMap",
    "full_name": "BostonGlobe/ShootingsMap",
    "created_at": "2017-07-24 18:47:54",
    "fork": false,
    "stargazers_count": 0,
    "forks_count": 0,
    "language": "JavaScript"
  },
  {
    "org": "bostonglobe",
    "name": "liquor-licenses",
    "full_name": "BostonGlobe/liquor-licenses",
    "created_at": "2017-08-11 20:49:04",
    "fork": false,
    "stargazers_count": 0,
    "forks_count": 0,
    "language": "HTML"
  },
  {
    "org": "bostonglobe",
    "name": "liquor-licenses-2",
    "full_name": "BostonGlobe/liquor-licenses-2",
    "created_at": "2017-08-11 20:49:39",
    "fork": false,
    "stargazers_count": 0,
    "forks_count": 0,
    "language": "HTML"
  },
  {
    "org": "bostonglobe",
    "name": "travelMap",
    "full_name": "BostonGlobe/travelMap",
    "created_at": "2017-09-12 17:47:55",
    "fork": false,
    "stargazers_count": 0,
    "forks_count": 0,
    "language": "JavaScript"
  },
  {
    "org": "bostonglobe",
    "name": "amazonhq2MA",
    "full_name": "BostonGlobe/amazonhq2MA",
    "created_at": "2017-09-22 19:59:33",
    "fork": false,
    "stargazers_count": 0,
    "forks_count": 0,
    "language": "JavaScript"
  },
  {
    "org": "bostonglobe",
    "name": "collegeStudents",
    "full_name": "BostonGlobe/collegeStudents",
    "created_at": "2017-10-26 13:39:34",
    "fork": false,
    "stargazers_count": 0,
    "forks_count": 0,
    "language": "JavaScript"
  },
  {
    "org": "bostonglobe",
    "name": "ShootingsTest",
    "full_name": "BostonGlobe/ShootingsTest",
    "created_at": "2017-11-10 23:13:33",
    "fork": false,
    "stargazers_count": 0,
    "forks_count": 0,
    "language": "JavaScript"
  },
  {
    "org": "bostonglobe",
    "name": "getRouthLatLngOSRM",
    "full_name": "BostonGlobe/getRouthLatLngOSRM",
    "created_at": "2018-01-11 15:45:49",
    "fork": false,
    "stargazers_count": 0,
    "forks_count": 0,
    "language": "JavaScript"
  },
  {
    "org": "bostonglobe",
    "name": "311request",
    "full_name": "BostonGlobe/311request",
    "created_at": "2018-01-12 21:45:44",
    "fork": false,
    "stargazers_count": 0,
    "forks_count": 0,
    "language": "JavaScript"
  },
  {
    "org": "bostonglobe",
    "name": "potholes18",
    "full_name": "BostonGlobe/potholes18",
    "created_at": "2018-01-27 00:12:58",
    "fork": false,
    "stargazers_count": 0,
    "forks_count": 0,
    "language": "HTML"
  },
  {
    "org": "bostonglobe",
    "name": "fluMap",
    "full_name": "BostonGlobe/fluMap",
    "created_at": "2018-02-08 14:12:03",
    "fork": false,
    "stargazers_count": 0,
    "forks_count": 0,
    "language": "HTML"
  },
  {
    "org": "bostonglobe",
    "name": "panda",
    "full_name": "BostonGlobe/panda",
    "created_at": "2018-04-20 14:19:51",
    "fork": true,
    "stargazers_count": 1,
    "forks_count": 0,
    "language": "Python"
  },
  {
    "org": "bostonglobe",
    "name": "web-map-maker",
    "full_name": "BostonGlobe/web-map-maker",
    "created_at": "2018-04-25 18:29:56",
    "fork": true,
    "stargazers_count": 0,
    "forks_count": 0,
    "language": "JavaScript"
  },
  {
    "org": "bostonglobe",
    "name": "Git-Commands",
    "full_name": "BostonGlobe/Git-Commands",
    "created_at": "2019-06-05 18:34:48",
    "fork": true,
    "stargazers_count": 0,
    "forks_count": 1,
    "language": null
  },
  {
    "org": "bostonglobe",
    "name": "ArcAds",
    "full_name": "BostonGlobe/ArcAds",
    "created_at": "2019-07-24 15:45:06",
    "fork": true,
    "stargazers_count": 0,
    "forks_count": 0,
    "language": "JavaScript"
  },
  {
    "org": "bostonglobe",
    "name": "arena",
    "full_name": "BostonGlobe/arena",
    "created_at": "2019-09-25 15:58:50",
    "fork": true,
    "stargazers_count": 0,
    "forks_count": 0,
    "language": null
  },
  {
    "org": "bostonglobe",
    "name": "gpt-mock",
    "full_name": "BostonGlobe/gpt-mock",
    "created_at": "2019-12-16 20:02:17",
    "fork": true,
    "stargazers_count": 0,
    "forks_count": 0,
    "language": null
  },
  {
    "org": "bostonglobe",
    "name": "js-d3-parliament",
    "full_name": "BostonGlobe/js-d3-parliament",
    "created_at": "2020-10-23 17:48:38",
    "fork": true,
    "stargazers_count": 2,
    "forks_count": 1,
    "language": "HTML"
  },
  {
    "org": "bostonglobe",
    "name": "nr-graphics-senate-impeachment",
    "full_name": "BostonGlobe/nr-graphics-senate-impeachment",
    "created_at": "2021-01-14 19:22:23",
    "fork": false,
    "stargazers_count": 0,
    "forks_count": 0,
    "language": "JavaScript"
  },
  {
    "org": "bostonglobe",
    "name": "wordpress-fieldmanager",
    "full_name": "BostonGlobe/wordpress-fieldmanager",
    "created_at": "2022-02-09 19:46:09",
    "fork": true,
    "stargazers_count": 0,
    "forks_count": 0,
    "language": null
  }
]