[
  {
    "org": "overview",
    "name": "overview-prototype",
    "created_at": "2011-12-28 20:14:29"
  },
  {
    "org": "overview",
    "name": "iraq-contractor-documents",
    "created_at": "2011-12-29 19:23:30"
  },
  {
    "org": "overview",
    "name": "overview-sample-files",
    "created_at": "2012-02-21 22:40:46"
  },
  {
    "org": "overview",
    "name": "overview-server",
    "created_at": "2012-05-18 21:00:17"
  },
  {
    "org": "overview",
    "name": "aws-overview-tools",
    "created_at": "2013-01-15 23:03:54"
  },
  {
    "org": "overview",
    "name": "aws-overview-config",
    "created_at": "2013-01-16 21:46:36"
  },
  {
    "org": "overview",
    "name": "js-mass-upload",
    "created_at": "2013-08-07 14:04:57"
  },
  {
    "org": "overview",
    "name": "docs2csv",
    "created_at": "2013-09-26 00:26:09"
  },
  {
    "org": "overview",
    "name": "phantomjs",
    "created_at": "2014-03-19 18:36:56"
  },
  {
    "org": "overview",
    "name": "search-and-count",
    "created_at": "2014-05-23 18:36:57"
  },
  {
    "org": "overview",
    "name": "overview-apps",
    "created_at": "2014-07-23 19:48:04"
  },
  {
    "org": "overview",
    "name": "mime-types",
    "created_at": "2014-08-06 20:40:19"
  },
  {
    "org": "overview",
    "name": "overview-word-cloud",
    "created_at": "2014-09-30 08:14:52"
  },
  {
    "org": "overview",
    "name": "overview-multi-search",
    "created_at": "2014-10-14 20:35:22"
  },
  {
    "org": "overview",
    "name": "overview-file-browser",
    "created_at": "2014-12-03 15:14:40"
  },
  {
    "org": "overview",
    "name": "osp",
    "created_at": "2014-12-15 15:53:54"
  },
  {
    "org": "overview",
    "name": "osp-map",
    "created_at": "2014-12-22 15:14:25"
  },
  {
    "org": "overview",
    "name": "overview-stupid-entities",
    "created_at": "2014-12-31 14:31:23"
  },
  {
    "org": "overview",
    "name": "ansible-pm2-plugins",
    "created_at": "2015-01-05 08:37:47"
  },
  {
    "org": "overview",
    "name": "script-add-files",
    "created_at": "2015-02-02 22:36:41"
  },
  {
    "org": "overview",
    "name": "osp-search",
    "created_at": "2015-02-11 23:28:01"
  },
  {
    "org": "overview",
    "name": "osp-network",
    "created_at": "2015-04-17 22:56:57"
  },
  {
    "org": "overview",
    "name": "overview-grep",
    "created_at": "2015-04-28 13:04:17"
  },
  {
    "org": "overview",
    "name": "osp-filter",
    "created_at": "2015-05-30 22:57:08"
  },
  {
    "org": "overview",
    "name": "osp-docs",
    "created_at": "2015-06-01 13:31:37"
  },
  {
    "org": "overview",
    "name": "overview-api-client-node",
    "created_at": "2015-06-11 19:54:00"
  },
  {
    "org": "overview",
    "name": "overview-js-tokenizer",
    "created_at": "2015-07-15 19:02:26"
  },
  {
    "org": "overview",
    "name": "overview-js-token-bin",
    "created_at": "2015-07-15 22:29:24"
  },
  {
    "org": "overview",
    "name": "overview-entity-filter",
    "created_at": "2015-07-20 18:12:10"
  },
  {
    "org": "overview",
    "name": "overview-js-bloom-filter",
    "created_at": "2015-07-22 22:18:34"
  },
  {
    "org": "overview",
    "name": "js-native-unordered-buffer-set",
    "created_at": "2015-07-27 19:21:54"
  },
  {
    "org": "overview",
    "name": "js-native-ternary-buffer-tree",
    "created_at": "2015-07-28 14:13:23"
  },
  {
    "org": "overview",
    "name": "overview-plugins-on-aws",
    "created_at": "2015-08-03 19:40:57"
  },
  {
    "org": "overview",
    "name": "overview-heartbeat",
    "created_at": "2015-08-05 15:50:48"
  },
  {
    "org": "overview",
    "name": "overview-docker",
    "created_at": "2015-08-21 19:39:35"
  },
  {
    "org": "overview",
    "name": "overview-local",
    "created_at": "2015-08-24 13:05:48"
  },
  {
    "org": "overview",
    "name": "pdfocr",
    "created_at": "2015-10-20 22:49:25"
  },
  {
    "org": "overview",
    "name": "overview-upload-directory",
    "created_at": "2017-03-12 21:40:18"
  },
  {
    "org": "overview",
    "name": "overview-pdf-viewer",
    "created_at": "2017-05-05 15:32:27"
  },
  {
    "org": "overview",
    "name": "overview-plugin-metadata",
    "created_at": "2017-07-25 17:52:07"
  },
  {
    "org": "overview",
    "name": "pdfocr-native",
    "created_at": "2017-12-15 00:14:19"
  },
  {
    "org": "overview",
    "name": "overview-integration-tester",
    "created_at": "2018-01-03 21:01:54"
  },
  {
    "org": "overview",
    "name": "overview-convert-archive",
    "created_at": "2018-03-14 20:06:18"
  },
  {
    "org": "overview",
    "name": "overview-convert-framework",
    "created_at": "2018-03-26 18:14:57"
  },
  {
    "org": "overview",
    "name": "overview-convert-image",
    "created_at": "2018-03-29 17:00:41"
  },
  {
    "org": "overview",
    "name": "overview-convert-office",
    "created_at": "2018-04-06 17:57:59"
  },
  {
    "org": "overview",
    "name": "overview-convert-pdfocr",
    "created_at": "2018-04-06 21:14:03"
  },
  {
    "org": "overview",
    "name": "overview-convert-pdf",
    "created_at": "2018-04-09 03:25:54"
  },
  {
    "org": "overview",
    "name": "overview-convert-text",
    "created_at": "2018-04-12 04:27:15"
  },
  {
    "org": "overview",
    "name": "html-to-pdf-benchmarks",
    "created_at": "2018-04-17 17:17:33"
  },
  {
    "org": "overview",
    "name": "overview-convert-html",
    "created_at": "2018-04-17 19:41:18"
  },
  {
    "org": "overview",
    "name": "overview-convert-email",
    "created_at": "2018-04-20 21:06:38"
  },
  {
    "org": "overview",
    "name": "overview-convert-pst",
    "created_at": "2018-04-23 17:28:18"
  },
  {
    "org": "overview",
    "name": "py-plugin-workqueue",
    "created_at": "2020-03-20 19:54:51"
  },
  {
    "org": "overview",
    "name": "overview.github.io",
    "created_at": "2020-07-08 21:46:58"
  }
]